odoo10_addon_web_readonly_bypass-10.0.1.0.1.99.dev4-py2.7-nspkg.pth
odoo/addons/web_readonly_bypass/README.rst
odoo/addons/web_readonly_bypass/__init__.py
odoo/addons/web_readonly_bypass/__manifest__.py
odoo/addons/web_readonly_bypass/i18n/web_readonly_bypass.pot
odoo/addons/web_readonly_bypass/static/description/icon.png
odoo/addons/web_readonly_bypass/static/src/js/readonly_bypass.js
odoo/addons/web_readonly_bypass/static/test/web_readonly_bypass.js
odoo/addons/web_readonly_bypass/tests/__init__.py
odoo/addons/web_readonly_bypass/tests/test_ui.py
odoo/addons/web_readonly_bypass/views/readonly_bypass.xml
odoo10_addon_web_readonly_bypass-10.0.1.0.1.99.dev4.dist-info/METADATA
odoo10_addon_web_readonly_bypass-10.0.1.0.1.99.dev4.dist-info/RECORD
odoo10_addon_web_readonly_bypass-10.0.1.0.1.99.dev4.dist-info/WHEEL
odoo10_addon_web_readonly_bypass-10.0.1.0.1.99.dev4.dist-info/namespace_packages.txt
odoo10_addon_web_readonly_bypass-10.0.1.0.1.99.dev4.dist-info/top_level.txt
