Metadata-Version: 2.1
Name: odoo10-addon-web-readonly-bypass
Version: 10.0.1.0.1.99.dev4
Summary: Allow to save onchange modifications to readonly fields
Home-page: http://www.acsone.eu
Author: ACSONE SA/NV, Odoo Community Association (OCA)
Author-email: support@odoo-community.org
License: LGPL-3
Platform: UNKNOWN
Classifier: Programming Language :: Python
Classifier: Framework :: Odoo
Classifier: License :: OSI Approved :: GNU Lesser General Public License v3 (LGPLv3)
Requires-Python: ~=2.7
Requires-Dist: odoo (<10.1dev,>=10.0)
